{
  "columns": [
    "date",
    "instrument_id",
    "ticker",
    "horizon_days",
    "label_name",
    "split_name",
    "split_role",
    "entry_date",
    "exit_date",
    "target_value",
    "target_type",
    "abs_ret_1d_lag1",
    "log_dollar_volume_lag1",
    "log_total_assets",
    "log_volume_lag1",
    "mkt_breadth_up_lag1",
    "mkt_coverage_ratio_lag1",
    "mkt_cross_sectional_vol_lag1",
    "mkt_equal_weight_return_lag1",
    "momentum_20d_excl_1d",
    "net_income_scale_proxy",
    "ret_1d_lag1",
    "ret_20d_lag1",
    "ret_5d_lag1",
    "revenue_scale_proxy",
    "shares_outstanding",
    "turnover_proxy_lag1",
    "vol_20d",
    "vol_5d",
    "run_id",
    "config_hash",
    "built_ts_utc"
  ],
  "created_at_utc": "2026-03-14T12:46:15.313813+00:00",
  "dataset_path": "C:\\Users\\manue\\Desktop\\JimSimons-1\\simons_smallcap_swing\\data\\datasets\\regression\\model_dataset.parquet",
  "dtypes": {
    "abs_ret_1d_lag1": "float64",
    "built_ts_utc": "object",
    "config_hash": "object",
    "date": "datetime64[ns]",
    "entry_date": "datetime64[ns]",
    "exit_date": "datetime64[ns]",
    "horizon_days": "int64",
    "instrument_id": "object",
    "label_name": "object",
    "log_dollar_volume_lag1": "float64",
    "log_total_assets": "float64",
    "log_volume_lag1": "float64",
    "mkt_breadth_up_lag1": "float64",
    "mkt_coverage_ratio_lag1": "float64",
    "mkt_cross_sectional_vol_lag1": "float64",
    "mkt_equal_weight_return_lag1": "float64",
    "momentum_20d_excl_1d": "float64",
    "net_income_scale_proxy": "float64",
    "ret_1d_lag1": "float64",
    "ret_20d_lag1": "float64",
    "ret_5d_lag1": "float64",
    "revenue_scale_proxy": "float64",
    "run_id": "object",
    "shares_outstanding": "float64",
    "split_name": "object",
    "split_role": "object",
    "target_type": "object",
    "target_value": "float64",
    "ticker": "object",
    "turnover_proxy_lag1": "float64",
    "vol_20d": "float64",
    "vol_5d": "float64"
  },
  "row_count": 228,
  "run_id": "checkpoint_w1_w5_model_dataset_regression",
  "schema_name": "model_dataset_mvp"
}