{
  "adjustment_modes_observed": [
    "split_only"
  ],
  "created_at_utc": "2026-03-13T23:16:31.375080+00:00",
  "gate_status": "PASS",
  "input_paths": {
    "adjusted_prices": "C:\\Users\\manue\\Desktop\\JimSimons-1\\simons_smallcap_swing\\data\\price\\adjusted_prices.parquet",
    "raw_prices": "C:\\Users\\manue\\Desktop\\JimSimons-1\\simons_smallcap_swing\\data\\price\\raw_prices.parquet",
    "ticker_history_map": "C:\\Users\\manue\\Desktop\\JimSimons-1\\simons_smallcap_swing\\data\\reference\\ticker_history_map.parquet",
    "trading_calendar": "C:\\Users\\manue\\Desktop\\JimSimons-1\\simons_smallcap_swing\\data\\reference\\trading_calendar.parquet"
  },
  "n_fail": 0,
  "n_rows": 252,
  "n_symbols": 4,
  "n_warn": 0,
  "pct_rows_ohlc_invalid": 0.0,
  "pct_symbols_bad_coverage": 0.0,
  "run_id": "week2_adjust_split_only_smoke_qc"
}