{
  "built_ts_utc": "2026-03-14T20:19:10.573832+00:00",
  "completed_fold_ids": [
    1,
    3,
    4
  ],
  "config_hash": "1f94e36da20b8826c2ea958dfd81978cce5db71bda5bf2c8c577c15f0f073e9d",
  "cv_method": "purged_kfold_full_history",
  "dummy_strategy": "mean",
  "folds_completed": 3,
  "folds_skipped": 2,
  "horizon_days": 20,
  "label_name": "fwd_ret_20d",
  "mean_n_train": 41.333333333333336,
  "mean_n_valid": 40.0,
  "mean_valid_primary_metric": 0.0011977626432938032,
  "median_valid_primary_metric": 0.0011389061082565928,
  "metric_aggregation_policy": "primary_metric_per_fold=mse; global_summary=mean/median/std over completed folds",
  "model_name": "dummy_regressor_cv",
  "module_version": "cross_validated_baselines_mvp_v1",
  "n_features_used_summary": {
    "max": 0.0,
    "mean": 0.0,
    "median": 0.0,
    "min": 0.0
  },
  "n_folds": 5,
  "notes": [
    "Only split_role in {train, valid} are used for fit/eval.",
    "dropped_by_purge and dropped_by_embargo are excluded from fit/eval.",
    "Dummy CV modes ignore feature matrix and learn target-only statistics per fold train set."
  ],
  "primary_metric": "mse",
  "run_id": "week8_improve_best_candidate_canonical_h20_no_fundamentals_dummy",
  "skipped_folds": [
    {
      "fold_id": 2,
      "reason": "missing train/valid rows (n_train=0, n_valid=48)"
    },
    {
      "fold_id": 5,
      "reason": "missing train/valid rows (n_train=116, n_valid=0)"
    }
  ],
  "source_paths": {
    "model_dataset": "C:\\Users\\manue\\Desktop\\JimSimons-1\\simons_smallcap_swing\\data\\research\\_improve_best_candidate_tmp_week8_improve_best_candidate_canonical_h20_20260314201910347664\\no_fundamentals_dataset.parquet",
    "purged_cv_folds": "C:\\Users\\manue\\Desktop\\JimSimons-1\\simons_smallcap_swing\\data\\labels\\purged_cv_folds.parquet"
  },
  "split_name": "holdout_temporal_purged",
  "std_valid_primary_metric": 0.0001468915161113257,
  "target_type": "continuous_forward_return",
  "used_feature_columns": []
}