{
  "built_ts_utc": "2026-03-14T19:35:03.541830+00:00",
  "completed_fold_ids": [
    1,
    2,
    3,
    4,
    5
  ],
  "config_hash": "d85ba16c537be11e987db6dc4afa26bc933851c46cd98dc13f626252cae168fa",
  "cv_method": "purged_kfold_full_history",
  "dummy_strategy": null,
  "folds_completed": 5,
  "folds_skipped": 0,
  "horizon_days": 5,
  "label_name": "fwd_ret_5d",
  "mean_n_train": 112.0,
  "mean_n_valid": 45.6,
  "mean_valid_primary_metric": 0.0001990595816878128,
  "median_valid_primary_metric": 0.00016605442672423018,
  "metric_aggregation_policy": "primary_metric_per_fold=mse; global_summary=mean/median/std over completed folds",
  "model_name": "ridge_cv",
  "module_version": "cross_validated_baselines_mvp_v1",
  "n_features_used_summary": {
    "max": 18.0,
    "mean": 17.4,
    "median": 18.0,
    "min": 15.0
  },
  "n_folds": 5,
  "notes": [
    "Only split_role in {train, valid} are used for fit/eval.",
    "dropped_by_purge and dropped_by_embargo are excluded from fit/eval."
  ],
  "primary_metric": "mse",
  "run_id": "week8_edge_real_feature_ablation_regression_all_features_ridge_cv",
  "skipped_folds": [],
  "source_paths": {
    "model_dataset": "C:\\Users\\manue\\Desktop\\JimSimons-1\\simons_smallcap_swing\\data\\research\\_feature_ablation_tmp_week8_edge_real_feature_ablation_20260314193503096295\\regression_all_features.parquet",
    "purged_cv_folds": "C:\\Users\\manue\\Desktop\\JimSimons-1\\simons_smallcap_swing\\data\\labels\\purged_cv_folds.parquet"
  },
  "split_name": "holdout_temporal_purged",
  "std_valid_primary_metric": 9.29233481830104e-05,
  "target_type": "continuous_forward_return",
  "used_feature_columns": [
    "abs_ret_1d_lag1",
    "log_dollar_volume_lag1",
    "log_total_assets",
    "log_volume_lag1",
    "mkt_breadth_up_lag1",
    "mkt_coverage_ratio_lag1",
    "mkt_cross_sectional_vol_lag1",
    "mkt_equal_weight_return_lag1",
    "momentum_20d_excl_1d",
    "net_income_scale_proxy",
    "ret_1d_lag1",
    "ret_20d_lag1",
    "ret_5d_lag1",
    "revenue_scale_proxy",
    "shares_outstanding",
    "turnover_proxy_lag1",
    "vol_20d",
    "vol_5d"
  ]
}